{"sections":{"main":{"type":"main-page","settings":{"padding_top":28,"padding_bottom":28}},"breadcrumbs_fGbdLV":{"type":"breadcrumbs","settings":{"text_alignment":"center"}},"collection_list_WrqELC":{"type":"collection-list","blocks":{"featured_collection_gDDM3i":{"type":"featured_collection","settings":{"collection":"op13-carrying-on-his-will","title":"","description":""}},"featured_collection_UK6EzW":{"type":"featured_collection","settings":{"collection":"op12-legacy-of-the-master","title":"","description":""}},"featured_collection_QBkGhE":{"type":"featured_collection","settings":{"collection":"eb02-anime-25th-collection","title":"","description":""}},"featured_collection_PbDm3b":{"type":"featured_collection","settings":{"collection":"op11","title":"","description":""}},"featured_collection_MHT9KH":{"type":"featured_collection","settings":{"collection":"op10","title":"","description":""}},"featured_collection_3ai4me":{"type":"featured_collection","settings":{"collection":"op09","title":"","description":""}},"featured_collection_wizHg4":{"type":"featured_collection","settings":{"collection":"op08","title":"","description":""}},"featured_collection_NFN3Rq":{"type":"featured_collection","settings":{"collection":"eb01","title":"","description":""}},"featured_collection_PRakiK":{"type":"featured_collection","settings":{"collection":"op07","title":"","description":""}},"featured_collection_GmrGtf":{"type":"featured_collection","settings":{"collection":"op06","title":"","description":""}},"featured_collection_6kJ9D4":{"type":"featured_collection","settings":{"collection":"op05","title":"","description":""}},"featured_collection_hLRBK7":{"type":"featured_collection","settings":{"collection":"op04","title":"","description":""}},"featured_collection_tXGztR":{"type":"featured_collection","settings":{"collection":"op03","title":"","description":""}},"featured_collection_kCmTKJ":{"type":"featured_collection","settings":{"collection":"op02","title":"","description":""}},"featured_collection_7qqjK9":{"type":"featured_collection","settings":{"collection":"op01","title":"","description":""}}},"block_order":["featured_collection_gDDM3i","featured_collection_UK6EzW","featured_collection_QBkGhE","featured_collection_PbDm3b","featured_collection_MHT9KH","featured_collection_3ai4me","featured_collection_wizHg4","featured_collection_NFN3Rq","featured_collection_PRakiK","featured_collection_GmrGtf","featured_collection_6kJ9D4","featured_collection_hLRBK7","featured_collection_tXGztR","featured_collection_kCmTKJ","featured_collection_7qqjK9"],"settings":{"color_scheme":"","layout":"standard","subheading":"","heading":"Collections","heading_size":"h1","heading_highlight_style":"none","description":"","text_size":"text-base","card_color_inherited":false,"show_product_count":true,"show_icon":true,"card_style":"","card_image_ratio":"adapt","content_alignment":"left","columns_desktop":4,"column_gap":"medium","row_gap":"medium","enable_slider":true,"columns_mobile":"1","swipe_on_mobile":true,"padding_top":50,"padding_bottom":50,"show_section_divider":false,"divider_width":"fixed"}},"featured_collection_bJ3Q3H":{"type":"featured-collection","settings":{"color_scheme":"","header_layout":"vertical","heading":"OP11 A Fist of Divine Speed","heading_size":"h1","heading_highlight_style":"none","subheading":"","description":"","text_size":"text-base","show_collection_description":false,"collection":"op11","limit":8,"columns":4,"column_gap":"medium","row_gap":"inherit","grid_layout":"standard","enable_slider":true,"controls_position":"inside","pcard_image_ratio":"","columns_mobile":"2","swipe_on_mobile":true,"show_all_button_on_top":false,"button_label":"","button_style":"btn--primary","padding_top":50,"padding_bottom":50,"show_section_divider":false,"divider_width":"fixed"}},"featured_collection_pbzFk9":{"type":"featured-collection","settings":{"color_scheme":"","header_layout":"vertical","heading":"OP10 Royal Blood","heading_size":"h1","heading_highlight_style":"none","subheading":"","description":"","text_size":"text-base","show_collection_description":false,"collection":"op10","limit":8,"columns":4,"column_gap":"medium","row_gap":"inherit","grid_layout":"standard","enable_slider":true,"controls_position":"inside","pcard_image_ratio":"","columns_mobile":"1","swipe_on_mobile":true,"show_all_button_on_top":false,"button_label":"","button_style":"btn--primary","padding_top":50,"padding_bottom":50,"show_section_divider":false,"divider_width":"fixed"}},"rich_text_8V8KHH":{"type":"rich-text","blocks":{"heading_Vwm4rM":{"type":"heading","settings":{"heading":"Can't look for the card you wanted?","heading_size":"hd1","heading_highlight_style":"none"}},"text_FdCrdK":{"type":"text","settings":{"text":"<p>Send us a message below<\/p>","text_size":"text-base"}},"button_VCTfgJ":{"type":"button","settings":{"button_label":"Message us","button_link":"shopify:\/\/pages\/about-cambridge-tcg","button_style":"btn--primary"}}},"block_order":["heading_Vwm4rM","text_FdCrdK","button_VCTfgJ"],"settings":{"color_scheme":"","content_alignment":"center","padding_top":50,"padding_bottom":50,"show_section_divider":false,"divider_width":"fixed"}}},"order":["main","breadcrumbs_fGbdLV","collection_list_WrqELC","featured_collection_bJ3Q3H","featured_collection_pbzFk9","rich_text_8V8KHH"]}